{
  "posts": [
    {
      "id": 1,
      "title": "json-server",
      "author": "typicode",
      "publishedAt": "2020-12-06"
    },
    {
      "id": 2,
      "title": "json-server2",
      "author": "typicode",
      "publishedAt": "2020-12-05"
    },
    {
      "id": 3,
      "title": "json-server3",
      "author": "typicode",
      "publishedAt": "2020-12-06"
    },
    {
      "title": "test",
      "author": "test",
      "publishedAt": "2020-10-16",
      "id": 4
    }
  ],
  "comments": [
    {
      "id": 1,
      "body": "some comment",
      "postId": 1
    }
  ],
  "profile": {
    "name": "john"
  }
}